loganom/__init__.py
loganom/config.py
loganom/exec_cmd.py
loganom/ipinfo.py
loganom/main.py
loganom/process_mail.py
loganom/processor.py
loganom/report.py
loganom/report_mail.py
loganom/report_mm.py
loganom/report_teams.py
loganom/utils.py
loganom-1.1.1.dist-info/LICENSE
loganom-1.1.1.dist-info/METADATA
loganom-1.1.1.dist-info/WHEEL
loganom-1.1.1.dist-info/entry_points.txt
loganom-1.1.1.dist-info/top_level.txt
loganom-1.1.1.dist-info/RECORD
