Metadata-Version: 2.1
Name: loganom
Version: 1.1.1
Summary: Log analyzer to discover anomalies
Home-page: https://github.com/dbaio/loganom
Author: Danilo G. Baio
Author-email: dbaio@bsd.com.br
License: BSD2CLAUSE
Project-URL: Documentation, https://loganom.readthedocs.io/en/latest/
Platform: any
Classifier: Programming Language :: Python :: 3
Classifier: License :: OSI Approved :: BSD License
Classifier: Operating System :: OS Independent
Classifier: Topic :: Communications :: Email
Requires-Python: >=3.9
License-File: LICENSE
Requires-Dist: dnspython
Requires-Dist: requests
Requires-Dist: marrow.mailer
Requires-Dist: texttable
Requires-Dist: pymsteams
